remics/__init__.py
remics/cumulants.jl
remics/cumulants.py
remics/cuna.py
remics/cures.py
remics-0.1.6.dist-info/LICENSE
remics-0.1.6.dist-info/METADATA
remics-0.1.6.dist-info/WHEEL
remics-0.1.6.dist-info/top_level.txt
remics-0.1.6.dist-info/RECORD
