Metadata-Version: 2.1
Name: remics
Version: 0.1.6
Summary: A Redescription-based framework for multi-omics analysis
Home-page: https://github.com/IBM/remics/
Author: Aritra Bose
Author-email: a.bose@ibm.com
Classifier: Programming Language :: Python :: 3
Classifier: License :: OSI Approved :: Apache Software License
Classifier: Operating System :: OS Independent
Requires-Python: >=3.9
License-File: LICENSE
